{
	"info": {
		"_postman_id": "306d3b51-67b1-4537-a7af-7ff9785b33be",
		"name": "Laravel-Task",
		"schema": "https://schema.getpostman.com/json/collection/v2.1.0/collection.json",
		"_exporter_id": "12896644"
	},
	"item": [
		{
			"name": "Customer",
			"item": [
				{
					"name": "Auth",
					"item": [
						{
							"name": "Login",
							"event": [
								{
									"listen": "test",
									"script": {
										"exec": [
											"var res = pm.response.json();\r",
											"pm.environment.set('token', res.token);"
										],
										"type": "text/javascript"
									}
								}
							],
							"request": {
								"method": "POST",
								"header": [
									{
										"warning": "This is a duplicate header and will be overridden by the Content-Type header generated by Postman.",
										"key": "Content-Type",
										"value": "application/json",
										"type": "text"
									},
									{
										"key": "X-Requested-With",
										"value": "XMLHttpRequest",
										"type": "text"
									}
								],
								"body": {
									"mode": "formdata",
									"formdata": [
										{
											"key": "email",
											"value": "customer1@example.com",
											"type": "text"
										},
										{
											"key": "password",
											"value": "12345678",
											"type": "text"
										}
									]
								},
								"url": {
									"raw": "{{url}}/customer/auth/login",
									"host": [
										"{{url}}"
									],
									"path": [
										"customer",
										"auth",
										"login"
									]
								}
							},
							"response": []
						},
						{
							"name": "customer",
							"event": [
								{
									"listen": "prerequest",
									"script": {
										"exec": [
											""
										],
										"type": "text/javascript"
									}
								},
								{
									"listen": "test",
									"script": {
										"exec": [
											""
										],
										"type": "text/javascript"
									}
								}
							],
							"protocolProfileBehavior": {
								"disableBodyPruning": true
							},
							"request": {
								"auth": {
									"type": "bearer",
									"bearer": [
										{
											"key": "token",
											"value": "{{token}}",
											"type": "string"
										}
									]
								},
								"method": "GET",
								"header": [
									{
										"key": "Content-Type",
										"value": "application/json",
										"type": "text"
									},
									{
										"key": "X-Requested-With",
										"value": "XMLHttpRequest",
										"type": "text"
									}
								],
								"body": {
									"mode": "formdata",
									"formdata": []
								},
								"url": {
									"raw": "{{url}}/customer/auth/user",
									"host": [
										"{{url}}"
									],
									"path": [
										"customer",
										"auth",
										"user"
									]
								}
							},
							"response": []
						}
					]
				}
			]
		},
		{
			"name": "User",
			"item": [
				{
					"name": "Auth",
					"item": [
						{
							"name": "Login",
							"event": [
								{
									"listen": "test",
									"script": {
										"exec": [
											"var res = pm.response.json();\r",
											"pm.environment.set('token', res.token);"
										],
										"type": "text/javascript"
									}
								}
							],
							"request": {
								"method": "POST",
								"header": [
									{
										"warning": "This is a duplicate header and will be overridden by the Content-Type header generated by Postman.",
										"key": "Content-Type",
										"value": "application/json",
										"type": "text"
									},
									{
										"key": "X-Requested-With",
										"value": "XMLHttpRequest",
										"type": "text"
									}
								],
								"body": {
									"mode": "formdata",
									"formdata": [
										{
											"key": "email",
											"value": "user1-1@example.com",
											"type": "text"
										},
										{
											"key": "password",
											"value": "12345678",
											"type": "text"
										}
									]
								},
								"url": {
									"raw": "{{url}}/user/auth/login",
									"host": [
										"{{url}}"
									],
									"path": [
										"user",
										"auth",
										"login"
									]
								}
							},
							"response": []
						},
						{
							"name": "User",
							"protocolProfileBehavior": {
								"disableBodyPruning": true
							},
							"request": {
								"auth": {
									"type": "bearer",
									"bearer": [
										{
											"key": "token",
											"value": "{{token}}",
											"type": "string"
										}
									]
								},
								"method": "GET",
								"header": [
									{
										"key": "Content-Type",
										"value": "application/json",
										"type": "text"
									},
									{
										"key": "X-Requested-With",
										"value": "XMLHttpRequest",
										"type": "text"
									}
								],
								"body": {
									"mode": "formdata",
									"formdata": []
								},
								"url": {
									"raw": "{{url}}/user/auth/user",
									"host": [
										"{{url}}"
									],
									"path": [
										"user",
										"auth",
										"user"
									]
								}
							},
							"response": []
						}
					]
				}
			]
		},
		{
			"name": "Admin",
			"item": [
				{
					"name": "Auth",
					"item": [
						{
							"name": "Login",
							"event": [
								{
									"listen": "test",
									"script": {
										"exec": [
											"var res = pm.response.json();\r",
											"pm.environment.set('token', res.token);"
										],
										"type": "text/javascript"
									}
								}
							],
							"request": {
								"method": "POST",
								"header": [
									{
										"warning": "This is a duplicate header and will be overridden by the Content-Type header generated by Postman.",
										"key": "Content-Type",
										"value": "application/json",
										"type": "text"
									},
									{
										"key": "X-Requested-With",
										"value": "XMLHttpRequest",
										"type": "text"
									}
								],
								"body": {
									"mode": "formdata",
									"formdata": [
										{
											"key": "email",
											"value": "admin1@example.com",
											"type": "text"
										},
										{
											"key": "password",
											"value": "12345678",
											"type": "text"
										}
									]
								},
								"url": {
									"raw": "{{url}}/admin/auth/login",
									"host": [
										"{{url}}"
									],
									"path": [
										"admin",
										"auth",
										"login"
									]
								}
							},
							"response": []
						},
						{
							"name": "User",
							"protocolProfileBehavior": {
								"disableBodyPruning": true
							},
							"request": {
								"auth": {
									"type": "bearer",
									"bearer": [
										{
											"key": "token",
											"value": "{{token}}",
											"type": "string"
										}
									]
								},
								"method": "GET",
								"header": [
									{
										"key": "Content-Type",
										"value": "application/json",
										"type": "text"
									},
									{
										"key": "X-Requested-With",
										"value": "XMLHttpRequest",
										"type": "text"
									}
								],
								"body": {
									"mode": "formdata",
									"formdata": []
								},
								"url": {
									"raw": "{{url}}/admin/auth/user",
									"host": [
										"{{url}}"
									],
									"path": [
										"admin",
										"auth",
										"user"
									]
								}
							},
							"response": []
						}
					]
				},
				{
					"name": "Invoice",
					"item": [
						{
							"name": "store",
							"request": {
								"auth": {
									"type": "bearer",
									"bearer": [
										{
											"key": "token",
											"value": "{{token}}",
											"type": "string"
										}
									]
								},
								"method": "POST",
								"header": [
									{
										"warning": "This is a duplicate header and will be overridden by the Content-Type header generated by Postman.",
										"key": "Content-Type",
										"value": "application/json",
										"type": "text"
									},
									{
										"key": "X-Requested-With",
										"value": "XMLHttpRequest",
										"type": "text"
									}
								],
								"body": {
									"mode": "formdata",
									"formdata": [
										{
											"key": "customer_id",
											"value": "1",
											"type": "text"
										},
										{
											"key": "start_date",
											"value": "2023-12-01",
											"type": "text"
										},
										{
											"key": "end_date",
											"value": "2023-12-31",
											"type": "text"
										}
									]
								},
								"url": {
									"raw": "{{url}}/admin/invoices/store",
									"host": [
										"{{url}}"
									],
									"path": [
										"admin",
										"invoices",
										"store"
									]
								}
							},
							"response": []
						},
						{
							"name": "show",
							"event": [
								{
									"listen": "prerequest",
									"script": {
										"exec": [
											""
										],
										"type": "text/javascript"
									}
								},
								{
									"listen": "test",
									"script": {
										"exec": [
											""
										],
										"type": "text/javascript"
									}
								}
							],
							"protocolProfileBehavior": {
								"disableBodyPruning": true
							},
							"request": {
								"auth": {
									"type": "bearer",
									"bearer": [
										{
											"key": "token",
											"value": "{{token}}",
											"type": "string"
										}
									]
								},
								"method": "GET",
								"header": [
									{
										"key": "Content-Type",
										"value": "application/json",
										"type": "text"
									},
									{
										"key": "X-Requested-With",
										"value": "XMLHttpRequest",
										"type": "text"
									}
								],
								"body": {
									"mode": "formdata",
									"formdata": []
								},
								"url": {
									"raw": "{{url}}/admin/invoices/show/1",
									"host": [
										"{{url}}"
									],
									"path": [
										"admin",
										"invoices",
										"show",
										"1"
									]
								}
							},
							"response": []
						}
					]
				}
			]
		}
	]
}